main.py
whist_score/__init__.py
whist_score/constants.py
whist_score/utils.py
whist_score/models/Game.py
whist_score/models/Player.py
whist_score/models/RoundTypes.py
whist_score/models/__init__.py
whist_score/views/__init__.py
whist_score/views/games.py
whist_score-0.1.13.dist-info/LICENSE
whist_score-0.1.13.dist-info/METADATA
whist_score-0.1.13.dist-info/WHEEL
whist_score-0.1.13.dist-info/entry_points.txt
whist_score-0.1.13.dist-info/top_level.txt
whist_score-0.1.13.dist-info/RECORD
